CHANGELOG.txt
LICENCE.txt
MANIFEST.in
README.txt
setup.py
pymspyt/__init__.py
pymspyt/main.py
pymspyt.egg-info/PKG-INFO
pymspyt.egg-info/SOURCES.txt
pymspyt.egg-info/dependency_links.txt
pymspyt.egg-info/entry_points.txt
pymspyt.egg-info/requires.txt
pymspyt.egg-info/top_level.txt
tempPython/lib/python3.7/site-packages/easy_install.py
tempPython/lib/python3.7/site-packages/typing_extensions.py
tempPython/lib/python3.7/site-packages/pip/__init__.py
tempPython/lib/python3.7/site-packages/pip/__main__.py
tempPython/lib/python3.7/site-packages/pip-18.1.dist-info/LICENSE.txt
tempPython/lib/python3.7/site-packages/pip-18.1.dist-info/entry_points.txt
tempPython/lib/python3.7/site-packages/pip-18.1.dist-info/top_level.txt
tempPython/lib/python3.7/site-packages/pip/_internal/__init__.py
tempPython/lib/python3.7/site-packages/pip/_internal/build_env.py
tempPython/lib/python3.7/site-packages/pip/_internal/cache.py
tempPython/lib/python3.7/site-packages/pip/_internal/configuration.py
tempPython/lib/python3.7/site-packages/pip/_internal/download.py
tempPython/lib/python3.7/site-packages/pip/_internal/exceptions.py
tempPython/lib/python3.7/site-packages/pip/_internal/index.py
tempPython/lib/python3.7/site-packages/pip/_internal/locations.py
tempPython/lib/python3.7/site-packages/pip/_internal/pep425tags.py
tempPython/lib/python3.7/site-packages/pip/_internal/pyproject.py
tempPython/lib/python3.7/site-packages/pip/_internal/resolve.py
tempPython/lib/python3.7/site-packages/pip/_internal/wheel.py
tempPython/lib/python3.7/site-packages/pip/_internal/cli/__init__.py
tempPython/lib/python3.7/site-packages/pip/_internal/cli/autocompletion.py
tempPython/lib/python3.7/site-packages/pip/_internal/cli/base_command.py
tempPython/lib/python3.7/site-packages/pip/_internal/cli/cmdoptions.py
tempPython/lib/python3.7/site-packages/pip/_internal/cli/main_parser.py
tempPython/lib/python3.7/site-packages/pip/_internal/cli/parser.py
tempPython/lib/python3.7/site-packages/pip/_internal/cli/status_codes.py
tempPython/lib/python3.7/site-packages/pip/_internal/commands/__init__.py
tempPython/lib/python3.7/site-packages/pip/_internal/commands/check.py
tempPython/lib/python3.7/site-packages/pip/_internal/commands/completion.py
tempPython/lib/python3.7/site-packages/pip/_internal/commands/configuration.py
tempPython/lib/python3.7/site-packages/pip/_internal/commands/download.py
tempPython/lib/python3.7/site-packages/pytube-10.5.1.dist-info/entry_points.txt
tempPython/lib/python3.7/site-packages/pytube-10.5.1.dist-info/top_level.txt
tempPython/lib/python3.7/site-packages/setuptools-40.6.2.dist-info/dependency_links.txt
tempPython/lib/python3.7/site-packages/setuptools-40.6.2.dist-info/entry_points.txt
tempPython/lib/python3.7/site-packages/setuptools-40.6.2.dist-info/top_level.txt
tempPython/lib/python3.7/site-packages/typing_extensions-3.7.4.3.dist-info/top_level.txt