Metadata-Version: 1.0
Name: pymspyt
Version: 0.1.3
Summary: Module CLI to install YouTube Video/Audio
Home-page: UNKNOWN
Author: Siva Pranav Mandadi
Author-email: msivapranav@gmail.com
License: MIT
Platform: UNKNOWN
